hardback/__init__.py
hardback/main.py
hardback/book/__init__.py
hardback/book/chunk_writer.py
hardback/book/css.py
hardback/book/cursor.py
hardback/book/hardback.py
hardback/book/metadata.py
hardback/book/page_breaker.py
hardback/book/sections.py
hardback/data/__init__.py
hardback/data/book.py
hardback/data/cover.py
hardback/data/dataclass.py
hardback/data/serialize.py
hardback/qr/__init__.py
hardback/qr/codes.py
hardback/qr/constants.py
hardback/qr/fill.py
hardback/qr/qr.py
hardback/qr/qr_table.py
hardback/qr/raw_codes.py
hardback/qr/write.py
hardback/util/__init__.py
hardback/util/chunk_sequence.py
hardback/util/elapsed_bar.py
hardback/util/files.py
hardback/util/hasher.py
test/hardback/__init__.py
test/hardback/all_test.py
test/hardback/skip_tests.py
test/hardback/book/__init__.py
test/hardback/book/hardback_test.py
test/hardback/data/__init__.py
test/hardback/data/cover_test.py
test/hardback/data/serialize_test.py
test/hardback/qr/__init__.py
test/hardback/qr/fill_test.py
test/hardback/qr/qr_table_test.py
test/hardback/util/__init__.py
test/hardback/util/chunk_sequence_test.py
hardback-0.9.2.dist-info/LICENSE
hardback-0.9.2.dist-info/METADATA
hardback-0.9.2.dist-info/WHEEL
hardback-0.9.2.dist-info/top_level.txt
hardback-0.9.2.dist-info/RECORD
