Metadata-Version: 2.1
Name: hardback
Version: 0.9.2
Summary: Hardcopy backups of digital data
Home-page: http://github.com/timedata-org/hardback
Author: Tom Ritchford
Author-email: tom@swirly.com
License: MIT
Download-URL: http://github.com/timedata-org/hardback/archive/0.9.2.tar.gz
Platform: UNKNOWN
Classifier: Development Status :: 4 - Beta
Classifier: License :: OSI Approved :: MIT License
Classifier: Programming Language :: Python :: 3.6
Classifier: Programming Language :: Python :: 3.7
Requires-Dist: EbookLib
Requires-Dist: attrs
Requires-Dist: cfgs
Requires-Dist: import-all
Requires-Dist: pillow
Requires-Dist: progress
Requires-Dist: pypng
Requires-Dist: pyyaml
Requires-Dist: segno
